{
  "en": [
    {
      "id": 0,
      "data_account": "5226411160001",
      "video_id": "6199926458001"
    },
    {
      "id": 1,
      "data_account": "5226411160001",
      "video_id": "6199924740001"
    },
    {
      "id": 2,
      "data_account": "5226411160001",
      "video_id": "6199925965001"
    },
    {
      "id": 3,
      "data_account": "5226411160001",
      "video_id": "6199924554001"
    },
    {
      "id": 4,
      "data_account": "5226411160001",
      "video_id": "6199925966001"
    },
    {
      "id": 5,
      "data_account": "5226411160001",
      "video_id": "6199924555001"
    }
  ],
  "es": [],
  "it": [],
  "fr": [],
  "ar": [],
  "vi": []
}
